{
  "name": "nifi",
  "manifests": [

  ],
  "charts": [
    {
      "repo": "oci://ghcr.io/konpyutaika/helm-charts",
      "chart": "nifikop",
      "version": "1.8.0"
    },
    {
      "repo": "oci://registry-1.docker.io/bitnamicharts",
      "chart": "zookeeper",
      "version": "12.0.0"
    }
  ],
  "images": [
    {
      "id": "nifi",
      "image": "docker.io/apache/nifi",
      "tag": "1.23.2"
    },
    {
      "id": "bash",
      "image": "docker.io/bash",
      "tag": "5.2.2"
    },
    {
      "id": "nifikop",
      "image": "ghcr.io/konpyutaika/docker-images/nifikop",
      "tag": "v1.8.0-release"
    },
    {
      "id": "zookeeper",
      "image": "docker.io/bitnami/zookeeper",
      "tag": "3.9.2-debian-12-r0"
    }
  ]

}
